wkyutils/__init__.py
wkyutils/data_structure_utils.py
wkyutils/database_utils.py
wkyutils/decimal_to_any.py
wkyutils/decorator_utils.py
wkyutils/engineer_measure_utils.py
wkyutils/excel_utils.py
wkyutils/image_utils.py
wkyutils/meta_class_utils.py
wkyutils/multiprocesses.py
wkyutils/multithreads.py
wkyutils/os_utils.py
wkyutils/plot_utils.py
wkyutils/print_utils.py
wkyutils/process_utils.py
wkyutils/regex_utils.py
wkyutils/reinforcement_learning_utils.py
wkyutils/send_message_utils.py
wkyutils/word_utils.py
wkyutils/xml_html_utils.py
wkyutils/auto_utils/__init__.py
wkyutils/auto_utils/auto_click/__init__.py
wkyutils/auto_utils/auto_click/auto_click_by_image_utils.py
wkyutils/auto_utils/auto_click/auto_click_by_point_utils.py
wkyutils/auto_utils/moniter/__init__.py
wkyutils/auto_utils/moniter/moniter_keyboard_utils.py
wkyutils/crawler_utils/__init__.py
wkyutils/crawler_utils/crawler_utils.py
wkyutils/deep_learning_utils/__init__.py
wkyutils/deep_learning_utils/CNN_utils/__init__.py
wkyutils/deep_learning_utils/CNN_utils/test.py
wkyutils/deep_learning_utils/CNN_utils/train_test.py
wkyutils/deep_learning_utils/CNN_utils/train_val_test_dataloaders.py
wkyutils/deep_learning_utils/CNN_utils/img_CNN_utils/__init__.py
wkyutils/deep_learning_utils/CNN_utils/img_CNN_utils/data_partition.py
wkyutils/deep_learning_utils/CNN_utils/img_CNN_utils/predict.py
wkyutils/deep_learning_utils/CNN_utils/img_CNN_utils/train_val_test_dataloader.py
wkyutils/deep_learning_utils/CNN_utils/str_CNN_utils/__init__.py
wkyutils/deep_learning_utils/CNN_utils/str_CNN_utils/train_val_test_dataloader.py
wkyutils-1.0.0.dist-info/LICENSE.txt
wkyutils-1.0.0.dist-info/METADATA
wkyutils-1.0.0.dist-info/WHEEL
wkyutils-1.0.0.dist-info/top_level.txt
wkyutils-1.0.0.dist-info/RECORD
